[
{"src":"music/Michael Learns To Rock - Take Me To Your Heart.mp3","img":"img/take.png","num":"9","musicName":"t me to u heart","name":"Michael"},
{"src":"music/邓超 - 超级英雄 (《奔跑吧兄弟》真人秀主题曲).mp3","img":"img/dengChao.png","num":"1","musicName":"超级英雄","name":"邓超"},
{"src":"music/TFBOYS - 大梦想家.mp3","img":"img/tf.png","num":"2","musicName":"大梦想家","name":"掏粪男孩"},
{"src":"music/莫文蔚 - 阴天.mp3","img":"img/mo.jpg","num":"3","musicName":"阴天","name":"莫文蔚"},
{"src":"music/李易峰 - 年少有你 (《栀子花开》电影正青春推广曲).mp3","img":"img/feng.jpg","num":"4","musicName":"年少有你","name":"李易峰"},
{"src":"music/张碧晨 - 年轮.mp3","img":"img/bi.jpg","num":"5","musicName":"年轮","name":"张碧晨"},
{"src":"music/G.E.M. 邓紫棋 - 喜欢你.mp3","img":"img/deng.jpg","num":"6","musicName":"喜欢你","name":"g.e.m.邓紫棋"},
{"src":"music/张靓颖 - 终于等到你 (《咱们结婚吧》电视剧片尾曲_《咱们结婚吧》电影主题曲).mp3","img":"img/zhangLiangYing.png","num":"7","musicName":"终于等到你","name":"张靓颖"},
{"src":"music/金志文 - 夏洛特烦恼.mp3","img":"img/jin.jpg","num":"8","musicName":"夏洛特烦恼","name":"金志文"},
{"src":"music/周杰伦 - 算什么男人.mp3","img":"img/zhouJL.png","num":"10","musicName":"算什么男人","name":"周杰伦"},
{"src":"music/李荣浩 - 出卖.mp3","img":"img/LRH.PNG","num":"11","musicName":"出卖","name":"李荣浩"},
{"src":"music/李荣浩 - 老街.mp3","img":"img/LRH.PNG","num":"12","musicName":"老街","name":"李荣浩"},
{"src":"music/李荣浩 - 喜剧之王.mp3","img":"img/LRH.PNG","num":"13","musicName":"喜剧之王","name":"李荣浩"},
{"src":"music/薛之谦 - 丑八怪.mp3","img":"img/XZQ.PNG","num":"14","musicName":"丑八怪","name":"薛之谦"},
{"src":"music/薛之谦 - 演员.mp3","img":"img/XZQ.PNG","num":"15","musicName":"演员","name":"薛之谦"}
 
]

	

	  		 